duckdns_updater/__init__.py
duckdns_updater/duckupdater.bat
duckdns_updater/icon.ico
duckdns_updater-1.0.0.dist-info/LICENSE
duckdns_updater-1.0.0.dist-info/METADATA
duckdns_updater-1.0.0.dist-info/WHEEL
duckdns_updater-1.0.0.dist-info/entry_points.txt
duckdns_updater-1.0.0.dist-info/top_level.txt
duckdns_updater-1.0.0.dist-info/RECORD
