Metadata-Version: 2.1
Name: duckdns-updater
Version: 1.0.0
Summary: A DuckDNS IP updater application.
Author: Jose Porcel
Classifier: License :: OSI Approved :: MIT License
Classifier: Programming Language :: Python :: 3.9
Classifier: Programming Language :: Python :: 3.10
Classifier: Programming Language :: Python :: 3.11
License-File: LICENSE
Requires-Dist: requests
Requires-Dist: pystray
Requires-Dist: Pillow
